README
setup.cfg
setup.py
odooenv/__init__.py
odooenv/addon.py
odooenv/defaults.py
odooenv/environment.py
odooenv/glhook.py
odooenv/installable.py
odooenv/repository.py
odooenv/server.py
odooenv/tools.py
odooenv.egg-info/PKG-INFO
odooenv.egg-info/SOURCES.txt
odooenv.egg-info/dependency_links.txt
odooenv.egg-info/requires.txt
odooenv.egg-info/top_level.txt
odooenv/data/defaults.yml
scripts/odooenv