Metadata-Version: 1.1
Name: odooenv
Version: 2.2.14
Summary: Odoo Environment Manager
Home-page: https://github.com/csrocha/odooenv
Author: Cristian S. Rocha
Author-email: csr@moldeo.coop
License: UNKNOWN
Download-URL: https://github.com/csrocha/odooenv/tarball/v2.2.3
Platform: UNKNOWN
Classifier: Development Status :: 5 - Production/Stable
Classifier: Environment :: Console
Classifier: Intended Audience :: Developers
Classifier: License :: OSI Approved :: GNU General Public License v3 or later (GPLv3+)
Classifier: Natural Language :: English
Classifier: Operating System :: Unix
Classifier: Programming Language :: Python :: 2.7
Classifier: Topic :: Software Development :: Build Tools
